{"censusYear":2022,"gdpYear":2023,"municipios":{"3200102":{"population":30684,"density":32.6,"areaKm2":941.188,"gdpBrlThousands":740220},"3200136":{"population":9711,"density":21.37,"areaKm2":454.448,"gdpBrlThousands":313558},"3200169":{"population":12042,"density":25.42,"areaKm2":473.729,"gdpBrlThousands":234307},"3200201":{"population":29177,"density":38.55,"areaKm2":756.86,"gdpBrlThousands":702107},"3200300":{"population":13836,"density":22.47,"areaKm2":615.677,"gdpBrlThousands":565385},"3200359":{"population":7434,"density":32.66,"areaKm2":227.617,"gdpBrlThousands":152485},"3200409":{"population":29984,"density":73.19,"areaKm2":409.691,"gdpBrlThousands":2317579},"3200508":{"population":7223,"density":37.24,"areaKm2":193.984,"gdpBrlThousands":146814},"3200607":{"population":94765,"density":66.72,"areaKm2":1420.285,"gdpBrlThousands":7724839},"3200706":{"population":10540,"density":45.26,"areaKm2":232.868,"gdpBrlThousands":453839},"3200805":{"population":30674,"density":33.74,"areaKm2":909.039,"gdpBrlThousands":910611},"3200904":{"population":42498,"density":44.99,"areaKm2":944.521,"gdpBrlThousands":1326677},"3201001":{"population":13608,"density":31.74,"areaKm2":428.716,"gdpBrlThousands":372418},"3201100":{"population":10254,"density":115.1,"areaKm2":89.084,"gdpBrlThousands":269758},"3201159":{"population":12985,"density":36.64,"areaKm2":354.404,"gdpBrlThousands":342658},"3201209":{"population":185786,"density":214.89,"areaKm2":864.583,"gdpBrlThousands":7593554},"3201308":{"population":353491,"density":1263.74,"areaKm2":279.718,"gdpBrlThousands":19710843},"3201407":{"population":36930,"density":55.66,"areaKm2":663.515,"gdpBrlThousands":1395638},"3201506":{"population":120033,"density":85.85,"areaKm2":1398.219,"gdpBrlThousands":5157945},"3201605":{"population":27458,"density":23.22,"areaKm2":1182.587,"gdpBrlThousands":676074},"3201704":{"population":11937,"density":32.28,"areaKm2":369.778,"gdpBrlThousands":356679},"3201803":{"population":5083,"density":29.21,"areaKm2":174.039,"gdpBrlThousands":101958},"3201902":{"population":35416,"density":28.81,"areaKm2":1229.21,"gdpBrlThousands":1294974},"3202009":{"population":6596,"density":41.41,"areaKm2":159.298,"gdpBrlThousands":232278},"3202108":{"population":21992,"density":9.62,"areaKm2":2285.369,"gdpBrlThousands":481243},"3202207":{"population":18014,"density":62.8,"areaKm2":286.854,"gdpBrlThousands":595415},"3202256":{"population":11009,"density":30.58,"areaKm2":360.016,"gdpBrlThousands":428413},"3202306":{"population":29358,"density":62.71,"areaKm2":468.185,"gdpBrlThousands":783590},"3202405":{"population":124656,"density":211.34,"areaKm2":589.825,"gdpBrlThousands":3391095},"3202454":{"population":25380,"density":105.63,"areaKm2":240.278,"gdpBrlThousands":560947},"3202504":{"population":11723,"density":58.25,"areaKm2":201.248,"gdpBrlThousands":359707},"3202553":{"population":9520,"density":28.77,"areaKm2":330.874,"gdpBrlThousands":206693},"3202603":{"population":12326,"density":60.56,"areaKm2":203.528,"gdpBrlThousands":385081},"3202652":{"population":13710,"density":74.19,"areaKm2":184.807,"gdpBrlThousands":280698},"3202702":{"population":13589,"density":25.4,"areaKm2":535.021,"gdpBrlThousands":453183},"3202801":{"population":39832,"density":72.33,"areaKm2":550.71,"gdpBrlThousands":6134486},"3202900":{"population":10597,"density":35.9,"areaKm2":295.189,"gdpBrlThousands":441241},"3203007":{"population":28590,"density":62.07,"areaKm2":460.586,"gdpBrlThousands":722976},"3203056":{"population":28931,"density":43.85,"areaKm2":659.751,"gdpBrlThousands":1252073},"3203106":{"population":11575,"density":65.27,"areaKm2":177.342,"gdpBrlThousands":218904},"3203130":{"population":14079,"density":49.45,"areaKm2":284.735,"gdpBrlThousands":615682},"3203163":{"population":11094,"density":24.2,"areaKm2":458.37,"gdpBrlThousands":272934},"3203205":{"population":166786,"density":47.7,"areaKm2":3496.263,"gdpBrlThousands":10014356},"3203304":{"population":12770,"density":39.73,"areaKm2":321.418,"gdpBrlThousands":250803},"3203320":{"population":41929,"density":321.87,"areaKm2":130.268,"gdpBrlThousands":7102418},"3203346":{"population":17641,"density":61.79,"areaKm2":285.495,"gdpBrlThousands":682791},"3203353":{"population":12387,"density":37.81,"areaKm2":327.642,"gdpBrlThousands":404453},"3203403":{"population":24475,"density":28.15,"areaKm2":869.439,"gdpBrlThousands":702863},"3203502":{"population":18900,"density":17.2,"areaKm2":1099.06,"gdpBrlThousands":564549},"3203601":{"population":5466,"density":10.11,"areaKm2":540.529,"gdpBrlThousands":136015},"3203700":{"population":18153,"density":26.74,"areaKm2":678.804,"gdpBrlThousands":509938},"3203809":{"population":13745,"density":42,"areaKm2":327.268,"gdpBrlThousands":307885},"3203908":{"population":49065,"density":34.08,"areaKm2":1439.571,"gdpBrlThousands":1886121},"3204005":{"population":18893,"density":22.55,"areaKm2":837.842,"gdpBrlThousands":467082},"3204054":{"population":21522,"density":49.65,"areaKm2":433.453,"gdpBrlThousands":545057},"3204104":{"population":23915,"density":24.58,"areaKm2":973.136,"gdpBrlThousands":1024676},"3204203":{"population":22300,"density":301.16,"areaKm2":74.046,"gdpBrlThousands":1056103},"3204252":{"population":6497,"density":18.04,"areaKm2":360.11,"gdpBrlThousands":141034},"3204302":{"population":13696,"density":23.02,"areaKm2":594.897,"gdpBrlThousands":7368211},"3204351":{"population":19274,"density":30.03,"areaKm2":641.929,"gdpBrlThousands":787898},"3204401":{"population":11069,"density":54.14,"areaKm2":204.464,"gdpBrlThousands":293579},"3204500":{"population":13106,"density":18.25,"areaKm2":718.325,"gdpBrlThousands":439644},"3204559":{"population":41636,"density":56.63,"areaKm2":735.198,"gdpBrlThousands":2592685},"3204609":{"population":22808,"density":33.39,"areaKm2":683.032,"gdpBrlThousands":820679},"3204658":{"population":8589,"density":28.77,"areaKm2":298.58,"gdpBrlThousands":391545},"3204708":{"population":32252,"density":74.16,"areaKm2":434.887,"gdpBrlThousands":988351},"3204807":{"population":10878,"density":39.77,"areaKm2":273.489,"gdpBrlThousands":230812},"3204906":{"population":123752,"density":52.75,"areaKm2":2346.049,"gdpBrlThousands":4355437},"3204955":{"population":10886,"density":31.84,"areaKm2":341.944,"gdpBrlThousands":301801},"3205002":{"population":520653,"density":950.74,"areaKm2":547.631,"gdpBrlThousands":37649155},"3205010":{"population":26502,"density":45.15,"areaKm2":587.036,"gdpBrlThousands":911932},"3205036":{"population":19563,"density":46.83,"areaKm2":417.76,"gdpBrlThousands":523374},"3205069":{"population":23831,"density":128.19,"areaKm2":185.909,"gdpBrlThousands":945412},"3205101":{"population":73423,"density":235.12,"areaKm2":312.279,"gdpBrlThousands":5957536},"3205150":{"population":8911,"density":20.57,"areaKm2":433.257,"gdpBrlThousands":213352},"3205176":{"population":13728,"density":29.19,"areaKm2":470.343,"gdpBrlThousands":615692},"3205200":{"population":467722,"density":2224.86,"areaKm2":210.225,"gdpBrlThousands":19711328},"3205309":{"population":322869,"density":3324.33,"areaKm2":97.123,"gdpBrlThousands":28257606}}}